gptw/__init__.py
gptw/gptw.py
gptw/prompts.json
gptw-0.6.0.dist-info/METADATA
gptw-0.6.0.dist-info/WHEEL
gptw-0.6.0.dist-info/entry_points.txt
gptw-0.6.0.dist-info/licenses/LICENSE
gptw-0.6.0.dist-info/RECORD
