Metadata-Version: 2.1
Name: gptw
Version: 0.6.0
Summary: The ChatGPT command-line wrapper simplifies the execution of predetermined tasks through ChatGPT.
Author: Xin Yang
Author-email: xinydev@gmail.com
License-Expression: Apache-2.0
License-File: LICENSE
Keywords: ChatGPT,Command Line,English Polishing,English Translation
Classifier: Development Status :: 3 - Alpha
Classifier: Intended Audience :: Developers
Classifier: License :: OSI Approved :: Apache Software License
Classifier: Natural Language :: English
Classifier: Programming Language :: Python
Classifier: Programming Language :: Python :: 3
Classifier: Programming Language :: Python :: 3.9
Classifier: Programming Language :: Python :: 3.10
Classifier: Programming Language :: Python :: 3.11
Requires-Python: >=3.7.1
Requires-Dist: openai>=1.0.0
Provides-Extra: testing
Requires-Dist: coverage==5.5; extra == 'testing'
Requires-Dist: pytest==7.1.3; extra == 'testing'
